restictool/__init__.py
restictool/__main__.py
restictool/argument_parser.py
restictool/configuration_parser.py
restictool/configuration_validator.py
restictool/entry_point.py
restictool/metrics.py
restictool/restic_tool.py
restictool/settings.py
restictool-0.7.0.dist-info/LICENSE
restictool-0.7.0.dist-info/METADATA
restictool-0.7.0.dist-info/WHEEL
restictool-0.7.0.dist-info/entry_points.txt
restictool-0.7.0.dist-info/top_level.txt
restictool-0.7.0.dist-info/RECORD
