Metadata-Version: 2.1
Name: restictool
Version: 0.7.0
Summary: A python wrapper for a dockerized restic tool
Author-email: Stanislav Meduna <stano@meduna.org>
Project-URL: Homepage, https://github.com/numo68/restictool
Project-URL: Bug Tracker, https://github.com/numo68/restictool/issues
Classifier: Programming Language :: Python :: 3
Classifier: License :: OSI Approved :: MIT License
Classifier: Operating System :: OS Independent
Requires-Python: >=3.10
License-File: LICENSE
Requires-Dist: PyYAML
Requires-Dist: docker
Requires-Dist: schema
Requires-Dist: setuptools
Requires-Dist: python-dateutil
Requires-Dist: prometheus-client
